ecnet/__init__.py
ecnet/callbacks.py
ecnet/model.py
ecnet/blends/__init__.py
ecnet/blends/equations.py
ecnet/blends/predict.py
ecnet/datasets/__init__.py
ecnet/datasets/load_data.py
ecnet/datasets/structs.py
ecnet/datasets/utils.py
ecnet/datasets/data/bp.smiles
ecnet/datasets/data/bp.target
ecnet/datasets/data/cn.smiles
ecnet/datasets/data/cn.target
ecnet/datasets/data/cp.smiles
ecnet/datasets/data/cp.target
ecnet/datasets/data/kv.smiles
ecnet/datasets/data/kv.target
ecnet/datasets/data/lhv.smiles
ecnet/datasets/data/lhv.target
ecnet/datasets/data/mon.smiles
ecnet/datasets/data/mon.target
ecnet/datasets/data/mp.smiles
ecnet/datasets/data/mp.target
ecnet/datasets/data/pp.smiles
ecnet/datasets/data/pp.target
ecnet/datasets/data/ron.smiles
ecnet/datasets/data/ron.target
ecnet/datasets/data/ysi.smiles
ecnet/datasets/data/ysi.target
ecnet/tasks/__init__.py
ecnet/tasks/feature_selection.py
ecnet/tasks/parameter_tuning.py
tests/test_all.py
ecnet-4.1.4.dist-info/LICENSE.txt
ecnet-4.1.4.dist-info/METADATA
ecnet-4.1.4.dist-info/WHEEL
ecnet-4.1.4.dist-info/top_level.txt
ecnet-4.1.4.dist-info/RECORD
