Metadata-Version: 2.1
Name: ecnet
Version: 4.1.4
Summary: Fuel property prediction using QSPR descriptors
Author-email: Travis Kessler <travis.j.kessler@gmail.com>
Project-URL: Homepage, https://github.com/ecrl/ecnet
Project-URL: Bug Tracker, https://github.com/ecrl/ecnet/issues
Classifier: Programming Language :: Python :: 3.11
Classifier: License :: OSI Approved :: MIT License
Classifier: Operating System :: OS Independent
Requires-Python: >=3.11
License-File: LICENSE.txt
Requires-Dist: torch ==2.4.0
Requires-Dist: scikit-learn ==1.5.1
Requires-Dist: padelpy ==0.1.16
Requires-Dist: alvadescpy ==0.1.3
Requires-Dist: ecabc ==3.0.1
